py3mschap/U32.py
py3mschap/__init__.py
py3mschap/des.py
py3mschap/des_c.py
py3mschap/des_data.py
py3mschap/md4.py
py3mschap/mppe.py
py3mschap/mschap.py
py3mschap/utils.py
raok-0.5.4.post1.data/scripts/raok-init.sh
raok-0.5.4.post1.data/scripts/raok.py
raok-0.5.4.post1.data/scripts/rasta.py
raok-0.5.4.post1.dist-info/METADATA
raok-0.5.4.post1.dist-info/WHEEL
raok-0.5.4.post1.dist-info/top_level.txt
raok-0.5.4.post1.dist-info/RECORD
