Metadata-Version: 2.1
Name: raok
Version: 0.5.4.post1
Summary: verbose TESTING radius authentication and accounting server and client
Home-page: https://github.com/astibal/raok
Author: Ales Stibal
Author-email: astib@mag0.net
License: UNKNOWN
Platform: UNKNOWN
Classifier: Programming Language :: Python :: 3
Classifier: License :: OSI Approved :: GNU Lesser General Public License v2 or later (LGPLv2+)
Classifier: Operating System :: OS Independent
Requires-Dist: py3mschap
Requires-Dist: pyrad
